paragon_py/__init__.py
paragon_py/utils.py
paragon_py/darwin_amd64/._simple_bench_darwin_amd64
paragon_py/darwin_amd64/._teleport.h
paragon_py/darwin_amd64/._teleport_amd64_darwin.dylib
paragon_py/darwin_amd64/._teleport_amd64_darwin.h
paragon_py/darwin_amd64/simple_bench_darwin_amd64
paragon_py/darwin_amd64/teleport.h
paragon_py/darwin_amd64/teleport_amd64_darwin.dylib
paragon_py/darwin_amd64/teleport_amd64_darwin.h
paragon_py/darwin_arm64/._simple_bench_darwin_arm64
paragon_py/darwin_arm64/._teleport.h
paragon_py/darwin_arm64/._teleport_arm64_darwin.dylib
paragon_py/darwin_arm64/._teleport_arm64_darwin.h
paragon_py/darwin_arm64/simple_bench_darwin_arm64
paragon_py/darwin_arm64/teleport.h
paragon_py/darwin_arm64/teleport_arm64_darwin.dylib
paragon_py/darwin_arm64/teleport_arm64_darwin.h
paragon_py/darwin_universal/._simple_bench_darwin_universal
paragon_py/darwin_universal/._teleport.h
paragon_py/darwin_universal/._teleport_universal_darwin.dylib
paragon_py/darwin_universal/simple_bench_darwin_universal
paragon_py/darwin_universal/teleport.h
paragon_py/darwin_universal/teleport_universal_darwin.dylib
paragon_py/linux_amd64/simple_bench_linux_amd64
paragon_py/linux_amd64/teleport.h
paragon_py/linux_amd64/teleport_amd64_linux.h
paragon_py/linux_amd64/teleport_amd64_linux.so
paragon_py/windows_amd64/libgcc_s_seh-1.dll
paragon_py/windows_amd64/libwinpthread-1.dll
paragon_py/windows_amd64/simple_bench_windows_amd64.exe
paragon_py/windows_amd64/teleport.h
paragon_py/windows_amd64/teleport_amd64_windows.dll
paragon_py/windows_amd64/teleport_amd64_windows.h
paragon_py-0.0.3.dist-info/licenses/LICENSE
paragon_py-0.0.3.dist-info/METADATA
paragon_py-0.0.3.dist-info/WHEEL
paragon_py-0.0.3.dist-info/top_level.txt
paragon_py-0.0.3.dist-info/RECORD
