Metadata-Version: 2.4
Name: paragon-py
Version: 0.0.3
Summary: Paragon AI — Python bindings (ctypes) with embedded cross-vendor GPU backends
Author: OpenFluke / Samuel Watson
License-Expression: Apache-2.0
Project-URL: Homepage, https://github.com/openfluke/paragon-py
Project-URL: Source, https://github.com/openfluke/paragon-py
Project-URL: Issues, https://github.com/openfluke/paragon-py/issues
Classifier: Programming Language :: Python :: 3
Classifier: Programming Language :: Python :: Implementation :: CPython
Classifier: Operating System :: OS Independent
Classifier: Topic :: Scientific/Engineering :: Artificial Intelligence
Requires-Python: >=3.8
License-File: LICENSE
Dynamic: license-file
